cli/__init__.py
cli/main.py
cli/diff/__init__.py
cli/diff/diff.py
cli/diff/commands/__init__.py
cli/diff/commands/diff_revision.py
cli/diff/commands/diff_upgrade.py
cli/get/__init__.py
cli/get/get.py
cli/get/commands/__init__.py
cli/get/commands/get_values.py
cli/history/__init__.py
cli/history/history.py
cli/list/__init__.py
cli/list/list.py
cli/pull/__init__.py
cli/pull/pull.py
cli/repo/__init__.py
cli/repo/repo.py
cli/repo/commands/__init__.py
cli/repo/commands/add.py
cli/repo/commands/list.py
cli/repo/commands/remove.py
cli/repo/commands/update.py
cli/rollback/__init__.py
cli/rollback/rollback.py
cli/status/__init__.py
cli/status/status.py
cli/template/__init__.py
cli/template/template.py
cli/uninstall/__init__.py
cli/uninstall/uninstall.py
cli/upgrade/__init__.py
cli/upgrade/upgrade.py
cli/utils/__init__.py
cli/utils/cli_utils.py
cli/utils/helm.py
cli/utils/kubectl.py
helm_hawk-0.0.7.dist-info/METADATA
helm_hawk-0.0.7.dist-info/WHEEL
helm_hawk-0.0.7.dist-info/entry_points.txt
helm_hawk-0.0.7.dist-info/top_level.txt
helm_hawk-0.0.7.dist-info/RECORD
