Metadata-Version: 2.1
Name: helm-hawk
Version: 0.0.7
Author: Ankit Singh
Author-email: as8356047@gmail.com
Classifier: Programming Language :: Python :: 3
Classifier: License :: OSI Approved :: MIT License
Classifier: Operating System :: OS Independent
Requires-Python: >=3.8
Requires-Dist: click
Requires-Dist: colorama
